[
    {
        "id":1,
        "name":"Ürün1",
        "price":175,
        "img":"/img/b1.jpg",
        "category":"mengene"
    },
    {
        "id":2,
        "name":"Ürün2",
        "price":175,
        "img":"/img/b2.jpg",
        "category":"mengene"
    },
    {
        "id":3,
        "name":"Ürün3",
        "price":175,
        "img":"/img/b3.jpg",
        "category":"mengene"
    },
    {
        "id":4,
        "name":"Ürün4",
        "price":200,
        "img":"/img/b4.jpg",
        "category":"kazaziye"
    },
    {
        "id":5,
        "name":"Ürün5",
        "price":175,
        "img":"/img/b5.jpg",
        "category":"mengene"
    },    
    {
        "id":6,
        "name":"Ürün6",
        "price":175,
        "img":"/img/b6.jpg",
        "category":"kazaziye"
    },
    {
        "id":7,
        "name":"Ürün7",
        "price":175,
        "img":"/img/b7.jpg",
        "category":"mengene"
    },
    {
        "id":8,
        "name":"Ürün8",
        "price":175,
        "img":"/img/b8.jpg",
        "category":"mengene"
    },
    {
        "id":9,
        "name":"Ürün9",
        "price":175,
        "img":"/img/b9.jpg",
        "category":"kazaziye"
    },
    {
        "id":10,
        "name":"Ürün10",
        "price":175,
        "img":"/img/b10.jpg",
        "category":"mengene"
    },
    {
        "id":11,
        "name":"Ürün11",
        "price":800,
        "img":"/img/g1.jpg",
        "category":"kazaziye"
    },
    {
        "id":12,
        "name":"Ürün12",
        "price":50,
        "img":"/img/nko1.jpg",
        "category":"nakis"
    },
    {
        "id":13,
        "name":"Ürün13",
        "price":50,
        "img":"/img/nko2.jpg",
        "category":"nakis"
    },
    {
        "id":14,
        "name":"Ürün14",
        "price":50,
        "img":"/img/nko3.jpg",
        "category":"nakis"
    },
    {
        "id":15,
        "name":"Ürün15",
        "price":50,
        "img":"/img/nko4.jpg",
        "category":"nakis"
    },
    {
        "id":16,
        "name":"Ürün16",
        "price":50,
        "img":"/img/nko5.jpg",
        "category":"nakis"
    },
    {
        "id":17,
        "name":"Ürün17",
        "price":50,
        "img":"/img/nko6.jpg",
        "category":"nakis"
    },
    {
        "id":18,
        "name":"Ürün18",
        "price":50,
        "img":"/img/nko7.jpg",
        "category":"nakis"
    },
    {
        "id":19,
        "name":"Ürün19",
        "price":50,
        "img":"/img/nko8.jpg",
        "category":"nakis"
    },
    {
        "id":20,
        "name":"Ürün20",
        "price":50,
        "img":"/img/nko9.jpg",
        "category":"nakis"
    },
    {
        "id":21,
        "name":"Ürün21",
        "price":200,
        "img":"/img/ns1.jpg",
        "category":"nakis"
    },
    {
        "id":22,
        "name":"Ürün22",
        "price":150,
        "img":"/img/ns2.jpg",
        "category":"nakis"
    },
    {
        "id":23,
        "name":"Ürün23",
        "price":200,
        "img":"/img/ns3.jpg",
        "category":"nakis"
    },
    {
        "id":24,
        "name":"Ürün24",
        "price":200,
        "img":"/img/ns4.jpg",
        "category":"nakis"
    },
    {
        "id":25,
        "name":"Ürün25",
        "price":100,
        "img":"/img/ns5.jpg",
        "category":"nakis"
    },
    {
        "id":26,
        "name":"Ürün26",
        "price":100,
        "img":"/img/ns6.jpg",
        "category":"nakis"
    },
    {
        "id":27,
        "name":"Ürün27",
        "price":100,
        "img":"/img/ns7.jpg",
        "category":"nakis"
    },
    {
        "id":28,
        "name":"Ürün28",
        "price":100,
        "img":"/img/ns8.jpg",
        "category":"nakis"
    },
    {
        "id":29,
        "name":"Ürün29",
        "price":50,
        "img":"/img/nki1.jpg",
        "category":"nakis"
    },
    {
        "id":30,
        "name":"Ürün30",
        "price":50,
        "img":"/img/nki2.jpg",
        "category":"nakis"
    },
    {
        "id":31,
        "name":"Ürün31",
        "price":50,
        "img":"/img/nki3.jpg",
        "category":"nakis"
    },
    {
        "id":32,
        "name":"Ürün32",
        "price":50,
        "img":"/img/nki4.jpg",
        "category":"nakis"
    },
    {
        "id":33,
        "name":"Ürün33",
        "price":50,
        "img":"/img/nii1.jpg",
        "category":"nakis"
    }
]